rotate/__init__.py
rotate/daemon.py
rotate/hooks.py
rotate/main.py
rotate/parse.py
rotate/rotate.py
rotate_mob-0.1.2.dist-info/METADATA
rotate_mob-0.1.2.dist-info/WHEEL
rotate_mob-0.1.2.dist-info/entry_points.txt
rotate_mob-0.1.2.dist-info/top_level.txt
rotate_mob-0.1.2.dist-info/RECORD
