Metadata-Version: 2.4
Name: rotate-mob
Version: 0.1.2
Summary: A CLI for mob programming rotations
Author-email: Nitsan Avni <nitsanav@gmail.com>
License: MIT
Project-URL: Homepage, https://github.com/nitsanavni/rotate
Requires-Python: >=3.12
